cbfeeds/__init__.py
cbfeeds/feed.py
cbfeeds_fork-1.0.1.dist-info/LICENSE.md
cbfeeds_fork-1.0.1.dist-info/METADATA
cbfeeds_fork-1.0.1.dist-info/WHEEL
cbfeeds_fork-1.0.1.dist-info/top_level.txt
cbfeeds_fork-1.0.1.dist-info/RECORD
