Metadata-Version: 2.1
Name: cbfeeds-fork
Version: 1.0.1
Summary: Carbon Black Alliance Feeds Forked
Home-page: https://github.com/mlodic/cbfeeds
Author: Matteo Lodi
Author-email: UNKNOWN
License: MIT
Platform: any
Classifier: Environment :: Web Environment
Classifier: Intended Audience :: Developers
Classifier: Operating System :: OS Independent
Classifier: Programming Language :: Python
Classifier: Topic :: Software Development :: Libraries :: Python Modules
Requires: requests
